{
    "account_db": "account%2F76%2F00%2Fefb3424dc4b79854521fd4563d0a",
    "account_id": "7600efb3424dc4b79854521fd4563d0a",
    "authorizing_id": "7a5bbeb0dc49a1d477a5cd0ae7bc8e7c",
    "authorizing_type": "device",
    "call_id": "4d9b215f5ac39dcf9115d247980b2993",
    "contact": "sip:user_zDc455@10.2.0.1:53764;methods=\"INVITE, ACK, BYE, CANCEL, OPTIONS, INFO, MESSAGE, SUBSCRIBE, NOTIFY, PRACK, UPDATE, REFER\"",
    "event_category": "notification",
    "event_name": "register",
    "event_timestamp": 63667524991,
    "expires": 540,
    "from_host": "imaginary.sip.local",
    "from_user": "user_zDc455",
    "network_ip": "192.168.0.1",
    "network_port": "53764",
    "owner_id": "7cef60382a96c0a6d187c150f60ab7e2",
    "realm": "imaginary.sip.local",
    "suppress_unregister_notify": false,
    "to_host": "imaginary.sip.local",
    "to_user": "user_zDc455",
    "user_agent": "PolycomVVX-VVX_310-UA/5.3.1.15347",
    "username": "user_zDc455"
}
